dsdl_2018/hw1/b05902121/full_adder.v
module full_adder(a,b,sum,cin,cout);

input a;
input b;
input cin;
output sum;
output cout;
wire tmp_sum, tmp1, tmp2;

xor xor0(tmp_sum,a,b);
xor xor1(sum,tmp_sum,cin);
and and0(tmp1,a,b);
and and0(tmp2,tmp_sum,cin);
or or0(cout,tmp1,tmp2);

endmodule

dsdl_2018/hw1/b05902121/full_adder_tb.v
`timescale 1ns/100ps

module half_adder_tb;
reg a;
reg b;
reg cin;
wire sum, cout;

initial begin
	$dumpfile("full_adder.vcd");
	$dumpvars;
end

initial begin
	a = 0; b = 0; cin =0;
	# 100 a = 0; b = 0; cin = 1;
	# 100 a = 0; b = 1; cin = 1;
	# 100 a = 1; b = 1; cin = 1;
	# 100 a = 1; b = 1; cin = 0;
	# 100 a = 0; b = 1; cin = 0;
	# 100 a = 1; b = 0; cin = 0;
	# 100 a = 1; b = 0; cin = 1;
	# 100
	$finish;
end

full_adder full_adder_0( .a(a), .b(b), .sum(sum), .cin(cin), .cout(cout));

endmodule

dsdl_2018/hw1/b05902121/full_adder.vcd
$date
	Mon Apr 30 16:56:33 2018
$end
$version
	Icarus Verilog
$end
$timescale
	100ps
$end
$scope module half_adder_tb $end
$var wire 1 ! sum $end
$var wire 1 " cout $end
$var reg 1 # a $end
$var reg 1 $ b $end
$var reg 1 % cin $end
$scope module full_adder_0 $end
$var wire 1 # a $end
$var wire 1 $ b $end
$var wire 1 % cin $end
$var wire 1 " cout $end
$var wire 1 ! sum $end
$var wire 1 & tmp1 $end
$var wire 1 ' tmp2 $end
$var wire 1 ( tmp_sum $end
$upscope $end
$upscope $end
$enddefinitions $end
#0
$dumpvars
0(
0'
0&
0%
0$
0#
0"
0!
$end
#1000
1!
1%
#2000
1"
0!
1'
1(
1$
#3000
1!
0'
0(
1&
1#
#4000
0!
0%
#5000
1!
0"
1(
0&
0#
#6000
0$
1#
#7000
1"
0!
1'
1%
